tactile_map/__init__.py
tactile_map/generate.py
tactile_map-0.0.1.dist-info/LICENSE
tactile_map-0.0.1.dist-info/METADATA
tactile_map-0.0.1.dist-info/WHEEL
tactile_map-0.0.1.dist-info/top_level.txt
tactile_map-0.0.1.dist-info/RECORD
