Metadata-Version: 2.1
Name: tactile-map
Version: 0.0.1
Summary: Generates designs of tactile maps recognisable by touch. For small scale production using laser cutters. For people who are blind or with a poor eyesight.
Home-page: https://github.com/matkoniecz/tactile_map
Author: Mateusz Konieczny
Author-email: matkoniecz@gmail.com
License: UNKNOWN
Platform: UNKNOWN
Classifier: Programming Language :: Python :: 3
Classifier: License :: OSI Approved :: GNU General Public License v3 (GPLv3)
Classifier: Operating System :: OS Independent
Requires-Dist: jsbeautifier (<2.0,>=1.13.5)
Requires-Dist: osm-bot-abstraction-layer (>=0.0.10)
Requires-Dist: shapely (<2.0,>=1..7.0)
Requires-Dist: tactile-patterns (>=0.0.1)
